openzim_mcp/__init__.py
openzim_mcp/__main__.py
openzim_mcp/async_operations.py
openzim_mcp/cache.py
openzim_mcp/config.py
openzim_mcp/constants.py
openzim_mcp/content_processor.py
openzim_mcp/defaults.py
openzim_mcp/error_messages.py
openzim_mcp/exceptions.py
openzim_mcp/instance_tracker.py
openzim_mcp/main.py
openzim_mcp/rate_limiter.py
openzim_mcp/security.py
openzim_mcp/server.py
openzim_mcp/simple_tools.py
openzim_mcp/timeout_utils.py
openzim_mcp/tool_decorator.py
openzim_mcp/types.py
openzim_mcp/zim_operations.py
openzim_mcp/tools/__init__.py
openzim_mcp/tools/content_tools.py
openzim_mcp/tools/file_tools.py
openzim_mcp/tools/metadata_tools.py
openzim_mcp/tools/navigation_tools.py
openzim_mcp/tools/search_tools.py
openzim_mcp/tools/server_tools.py
openzim_mcp/tools/structure_tools.py
openzim_mcp-0.8.3.dist-info/licenses/LICENSE
openzim_mcp-0.8.3.dist-info/METADATA
openzim_mcp-0.8.3.dist-info/WHEEL
openzim_mcp-0.8.3.dist-info/entry_points.txt
openzim_mcp-0.8.3.dist-info/top_level.txt
openzim_mcp-0.8.3.dist-info/RECORD
