Metadata-Version: 2.4
Name: openzim-mcp
Version: 0.8.3
Summary: OpenZIM MCP - ZIM MCP Server that enables AI models to access and search ZIM format knowledge bases offline
Author-email: Cameron Rye <c@meron.io>
Maintainer-email: Cameron Rye <c@meron.io>
License-Expression: MIT
Project-URL: Homepage, https://github.com/cameronrye/openzim-mcp
Project-URL: Repository, https://github.com/cameronrye/openzim-mcp.git
Project-URL: Issues, https://github.com/cameronrye/openzim-mcp/issues
Project-URL: Changelog, https://github.com/cameronrye/openzim-mcp/blob/main/CHANGELOG.md
Project-URL: Documentation, https://github.com/cameronrye/openzim-mcp#readme
Project-URL: Security Policy, https://github.com/cameronrye/openzim-mcp/blob/main/SECURITY.md
Project-URL: Contributing, https://github.com/cameronrye/openzim-mcp/blob/main/CONTRIBUTING.md
Keywords: zim,openzim,mcp,model-context-protocol,ai,llm,knowledge-base,offline,wikipedia,search,libzim
Classifier: Development Status :: 4 - Beta
Classifier: Intended Audience :: Developers
Classifier: Intended Audience :: Science/Research
Classifier: Operating System :: OS Independent
Classifier: Programming Language :: Python :: 3
Classifier: Programming Language :: Python :: 3.12
Classifier: Programming Language :: Python :: 3.13
Classifier: Programming Language :: Python :: 3 :: Only
Classifier: Topic :: Scientific/Engineering :: Artificial Intelligence
Classifier: Topic :: Software Development :: Libraries :: Python Modules
Classifier: Topic :: Text Processing :: Indexing
Classifier: Topic :: Internet :: WWW/HTTP :: Indexing/Search
Classifier: Topic :: Database
Classifier: Typing :: Typed
Requires-Python: >=3.12
License-File: LICENSE
Requires-Dist: beautifulsoup4>=4.14.2
Requires-Dist: html2text>=2025.4.15
Requires-Dist: libzim>=3.8.0
Requires-Dist: mcp[cli]>=1.23.0
Requires-Dist: pydantic>=2.12.0
Requires-Dist: pydantic-settings>=2.12.0
Dynamic: license-file
